project_abstraction/__init__.py
project_abstraction/base.py
project_abstraction/sample.py
project_abstraction-0.5.1.dist-info/DESCRIPTION.rst
project_abstraction-0.5.1.dist-info/METADATA
project_abstraction-0.5.1.dist-info/RECORD
project_abstraction-0.5.1.dist-info/WHEEL
project_abstraction-0.5.1.dist-info/metadata.json
project_abstraction-0.5.1.dist-info/top_level.txt
